[
    {
        "id": "636db09b-3acc-3701-b805-a457a7bc5767",
        "deviceId": "62668f2f-4526-4d61-a3da-2e9e3d764584",
        "category": "SCHEDULE",
        "type": "SCHEDULE_STATUS",
        "eventDate": 1733842486000,
        "summary": "Lawn Sprinklers will run for 19 minutes.",
        "subType": "SCHEDULE_STARTED",
        "hidden": false,
        "scheduleId": "f7e02fa5-b1fc-4514-9f64-d76ccdd520d8",
        "topic": "WATERING"
    },
    {
        "id": "63311407-edf0-39cc-9d17-d37f5d8e1b3e",
        "deviceId": "62668f2f-4526-4d61-a3da-2e9e3d764584",
        "type": "ZONE_STATUS",
        "eventDate": 1733842487000,
        "summary": "Backyard Northwest began watering at 06:54 AM (PST).",
        "subType": "ZONE_STARTED",
        "hidden": false,
        "topic": "WATERING"
    },
    {
        "id": "68e209f1-93f6-310c-8123-63f4bdb3f5de",
        "deviceId": "62668f2f-4526-4d61-a3da-2e9e3d764584",
        "category": "SCHEDULE",
        "eventDate": 1733842578000,
        "summary": "Lawn Sprinklers was not skipped because the PLUS weather network observed:\n0.00 in of predicted and 0.00 in observed precipitation\n3 mph winds\n34\u00b0F temp",
        "hidden": false,
        "scheduleId": "f7e02fa5-b1fc-4514-9f64-d76ccdd520d8"
    },
    {
        "id": "97eb2fa5-d8f4-35c3-9148-478cabcc5164",
        "deviceId": "62668f2f-4526-4d61-a3da-2e9e3d764584",
        "type": "ZONE_STATUS",
        "eventDate": 1733842736000,
        "summary": "Backyard Middle West began watering at 06:58 AM (PST).",
        "subType": "ZONE_STARTED",
        "hidden": false,
        "topic": "WATERING"
    },
    {
        "id": "c283d62f-00cd-375a-8732-736aa82a57ad",
        "deviceId": "62668f2f-4526-4d61-a3da-2e9e3d764584",
        "type": "ZONE_STATUS",
        "eventDate": 1733842746000,
        "summary": "Backyard Northwest completed watering at 06:59 AM (PST) for 4 minutes.",
        "subType": "ZONE_COMPLETED",
        "hidden": false,
        "topic": "WATERING"
    },
    {
        "id": "1ed1a2dd-9455-33e4-867b-582dc20bb0c3",
        "deviceId": "62668f2f-4526-4d61-a3da-2e9e3d764584",
        "type": "ZONE_STATUS",
        "eventDate": 1733842963000,
        "summary": "Backyard South West began watering at 07:02 AM (PST).",
        "subType": "ZONE_STARTED",
        "hidden": false,
        "topic": "WATERING"
    },
    {
        "id": "3604ffe9-9d61-3b43-864b-979f5c1f1ce8",
        "deviceId": "62668f2f-4526-4d61-a3da-2e9e3d764584",
        "type": "ZONE_STATUS",
        "eventDate": 1733842974000,
        "summary": "Backyard Middle West completed watering at 07:02 AM (PST) for 4 minutes.",
        "subType": "ZONE_COMPLETED",
        "hidden": false,
        "topic": "WATERING"
    },
    {
        "id": "4ae9ac89-dd01-33b4-82cf-242c9e31b22b",
        "deviceId": "62668f2f-4526-4d61-a3da-2e9e3d764584",
        "type": "ZONE_STATUS",
        "eventDate": 1733843148000,
        "summary": "Backyard East Lawn began watering at 07:05 AM (PST).",
        "subType": "ZONE_STARTED",
        "hidden": false,
        "topic": "WATERING"
    },
    {
        "id": "679e056a-691c-3a80-bf11-fe811f480acb",
        "deviceId": "62668f2f-4526-4d61-a3da-2e9e3d764584",
        "type": "ZONE_STATUS",
        "eventDate": 1733843158000,
        "summary": "Backyard South West completed watering at 07:05 AM (PST) for 3 minutes.",
        "subType": "ZONE_COMPLETED",
        "hidden": false,
        "topic": "WATERING"
    },
    {
        "id": "72b65de8-fe42-3c22-9e4e-a33fbe129161",
        "deviceId": "62668f2f-4526-4d61-a3da-2e9e3d764584",
        "type": "ZONE_STATUS",
        "eventDate": 1733843641000,
        "summary": "Backyard East Lawn completed watering at 07:14 AM (PST) for 8 minutes.",
        "subType": "ZONE_COMPLETED",
        "hidden": false,
        "topic": "WATERING"
    },
    {
        "id": "f32cda37-01b1-3dc3-8fab-ebcbe1940485",
        "deviceId": "62668f2f-4526-4d61-a3da-2e9e3d764584",
        "category": "SCHEDULE",
        "type": "SCHEDULE_STATUS",
        "eventDate": 1733843642000,
        "summary": "Lawn Sprinklers ran for 19 minutes.",
        "subType": "SCHEDULE_COMPLETED",
        "hidden": false,
        "scheduleId": "f7e02fa5-b1fc-4514-9f64-d76ccdd520d8",
        "topic": "WATERING"
    },
    {
        "id": "3d784809-ecda-3528-b127-63f00de7760f",
        "deviceId": "62668f2f-4526-4d61-a3da-2e9e3d764584",
        "category": "SCHEDULE",
        "type": "WEATHER_INTELLIGENCE",
        "eventDate": 1734102172000,
        "summary": "Lawn Sprinklers was scheduled for 12/13 at 06:57 AM (PST), but was skipped due to PLUS weather network which observed 0.46 in precipitation compared to schedules's threshold of 0.13 in.",
        "subType": "WEATHER_INTELLIGENCE_SKIP",
        "hidden": false,
        "scheduleId": "f7e02fa5-b1fc-4514-9f64-d76ccdd520d8",
        "topic": "SCHEDULE"
    }
]