[
    {
        "id": "9932f9dc-9a56-3554-9bb5-77d6bca4fc22",
        "deviceId": "62668f2f-4526-4d61-a3da-2e9e3d764584",
        "category": "SCHEDULE",
        "type": "SCHEDULE_STATUS",
        "eventDate": 1760278382000,
        "summary": "Lawn Sprinklers ran for 60 minutes.",
        "subType": "SCHEDULE_COMPLETED",
        "hidden": false,
        "scheduleId": "f7e02fa5-b1fc-4514-9f64-d76ccdd520d8",
        "topic": "WATERING"
    },
    {
        "id": "67b8b0b4-ebb3-37b5-9e08-3ebc88ab1edd",
        "deviceId": "62668f2f-4526-4d61-a3da-2e9e3d764584",
        "type": "ZONE_STATUS",
        "eventDate": 1760278381000,
        "summary": "Backyard East Lawn completed watering at 07:13 AM (PDT) for 7 minutes.",
        "subType": "ZONE_COMPLETED",
        "hidden": false,
        "topic": "WATERING"
    },
    {
        "id": "1df88a8c-27e8-373f-bd49-ff29737539d2",
        "deviceId": "62668f2f-4526-4d61-a3da-2e9e3d764584",
        "type": "ZONE_STATUS",
        "eventDate": 1760277954000,
        "summary": "Backyard Middle We... completed watering at 07:05 AM (PDT) for 4 minutes.",
        "subType": "ZONE_COMPLETED",
        "hidden": false,
        "topic": "WATERING"
    },
    {
        "id": "6f6709ad-7ce9-3014-8b3e-aa0291a04d32",
        "deviceId": "62668f2f-4526-4d61-a3da-2e9e3d764584",
        "type": "ZONE_STATUS",
        "eventDate": 1760277944000,
        "summary": "Backyard East Lawn began watering at 07:05 AM (PDT).",
        "subType": "ZONE_STARTED",
        "hidden": false,
        "topic": "WATERING"
    },
    {
        "id": "145dd9ee-be16-31be-a77a-c77ba7743337",
        "deviceId": "62668f2f-4526-4d61-a3da-2e9e3d764584",
        "type": "ZONE_STATUS",
        "eventDate": 1760277695000,
        "summary": "Backyard Northwest completed watering at 07:01 AM (PDT) for 5 minutes.",
        "subType": "ZONE_COMPLETED",
        "hidden": false,
        "topic": "WATERING"
    },
    {
        "id": "c71f0e84-f72f-3dc4-ac60-f83ac1447bb7",
        "deviceId": "62668f2f-4526-4d61-a3da-2e9e3d764584",
        "type": "ZONE_STATUS",
        "eventDate": 1760277685000,
        "summary": "Backyard Middle We... began watering at 07:01 AM (PDT).",
        "subType": "ZONE_STARTED",
        "hidden": false,
        "topic": "WATERING"
    },
    {
        "id": "617c37f6-d4ec-35f3-8089-bc82339179aa",
        "deviceId": "62668f2f-4526-4d61-a3da-2e9e3d764584",
        "type": "ZONE_STATUS",
        "eventDate": 1760277400000,
        "summary": "Backyard Northwest began watering at 06:56 AM (PDT).",
        "subType": "ZONE_STARTED",
        "hidden": false,
        "topic": "WATERING"
    },
    {
        "id": "3c0e1260-c697-336a-b4db-71836cb1246e",
        "deviceId": "62668f2f-4526-4d61-a3da-2e9e3d764584",
        "type": "DEVICE_STATUS",
        "eventDate": 1760277398000,
        "summary": "Soaked Backyard East Lawn for 21 minutes, completed at 06:56 AM (PDT).",
        "subType": "ZONE_CYCLING_COMPLETED",
        "hidden": false,
        "topic": "WATERING"
    },
    {
        "id": "85dba0c4-a22a-3cd2-beaa-90d16786da81",
        "deviceId": "62668f2f-4526-4d61-a3da-2e9e3d764584",
        "type": "ZONE_STATUS",
        "eventDate": 1760276155000,
        "summary": "Soaking Backyard East Lawn for 21 minutes, started at 06:35 AM (PDT).",
        "subType": "ZONE_CYCLING",
        "hidden": false,
        "topic": "WATERING"
    },
    {
        "id": "4960f6b9-8d50-3d1b-81d9-7449e4ecd58d",
        "deviceId": "62668f2f-4526-4d61-a3da-2e9e3d764584",
        "type": "ZONE_STATUS",
        "eventDate": 1760276154000,
        "summary": "Backyard East Lawn completed watering at 06:35 AM (PDT) for 7 minutes.",
        "subType": "ZONE_COMPLETED",
        "hidden": false,
        "topic": "WATERING"
    },
    {
        "id": "4e8c54b0-603d-3c8f-a6a6-7ae1281ae691",
        "deviceId": "62668f2f-4526-4d61-a3da-2e9e3d764584",
        "type": "ZONE_STATUS",
        "eventDate": 1760275726000,
        "summary": "Backyard South Wes... completed watering at 06:28 AM (PDT) for 6 minutes.",
        "subType": "ZONE_COMPLETED",
        "hidden": false,
        "topic": "WATERING"
    },
    {
        "id": "b69c5ead-177e-3bde-8e47-3544bded1b68",
        "deviceId": "62668f2f-4526-4d61-a3da-2e9e3d764584",
        "type": "ZONE_STATUS",
        "eventDate": 1760275716000,
        "summary": "Backyard East Lawn began watering at 06:28 AM (PDT).",
        "subType": "ZONE_STARTED",
        "hidden": false,
        "topic": "WATERING"
    },
    {
        "id": "a2ddc04d-b63e-325a-b824-e5901e535938",
        "deviceId": "62668f2f-4526-4d61-a3da-2e9e3d764584",
        "type": "ZONE_STATUS",
        "eventDate": 1760275356000,
        "summary": "Backyard Middle We... completed watering at 06:22 AM (PDT) for 4 minutes.",
        "subType": "ZONE_COMPLETED",
        "hidden": false,
        "topic": "WATERING"
    },
    {
        "id": "4ed1ef80-c954-359a-855b-20d314e9c578",
        "deviceId": "62668f2f-4526-4d61-a3da-2e9e3d764584",
        "type": "ZONE_STATUS",
        "eventDate": 1760275346000,
        "summary": "Backyard South Wes... began watering at 06:22 AM (PDT).",
        "subType": "ZONE_STARTED",
        "hidden": false,
        "topic": "WATERING"
    },
    {
        "id": "a3e8863c-8a91-3708-80d6-7fef7dfdee22",
        "deviceId": "62668f2f-4526-4d61-a3da-2e9e3d764584",
        "type": "ZONE_STATUS",
        "eventDate": 1760275097000,
        "summary": "Backyard Northwest completed watering at 06:18 AM (PDT) for 5 minutes.",
        "subType": "ZONE_COMPLETED",
        "hidden": false,
        "topic": "WATERING"
    },
    {
        "id": "e19bfa0b-d67b-3636-8076-2408b3f6adb1",
        "deviceId": "62668f2f-4526-4d61-a3da-2e9e3d764584",
        "type": "ZONE_STATUS",
        "eventDate": 1760275088000,
        "summary": "Backyard Middle We... began watering at 06:18 AM (PDT).",
        "subType": "ZONE_STARTED",
        "hidden": false,
        "topic": "WATERING"
    },
    {
        "id": "53147033-1fdf-3fd2-b099-1be8825aa61a",
        "deviceId": "62668f2f-4526-4d61-a3da-2e9e3d764584",
        "category": "SCHEDULE",
        "eventDate": 1760275005000,
        "summary": "Lawn Sprinklers was not skipped because the PLUS weather network observed:\n0.00 in of predicted and 0.00 in observed precipitation\n10 mph winds\n50\u00b0F temp",
        "hidden": false,
        "scheduleId": "f7e02fa5-b1fc-4514-9f64-d76ccdd520d8"
    },
    {
        "id": "1e248731-af0a-303c-b320-9588edf77eb0",
        "deviceId": "62668f2f-4526-4d61-a3da-2e9e3d764584",
        "type": "ZONE_STATUS",
        "eventDate": 1760274801000,
        "summary": "Backyard Northwest began watering at 06:13 AM (PDT).",
        "subType": "ZONE_STARTED",
        "hidden": false,
        "topic": "WATERING"
    },
    {
        "id": "d3e4bcbf-3ce6-300b-8334-13f9f24d5422",
        "deviceId": "62668f2f-4526-4d61-a3da-2e9e3d764584",
        "category": "SCHEDULE",
        "type": "SCHEDULE_STATUS",
        "eventDate": 1760274800000,
        "summary": "Lawn Sprinklers will run for 60 minutes.",
        "subType": "SCHEDULE_STARTED",
        "hidden": false,
        "scheduleId": "f7e02fa5-b1fc-4514-9f64-d76ccdd520d8",
        "topic": "WATERING"
    },
    {
        "id": "3b286bde-8da8-3acb-9265-bb92149f898d",
        "deviceId": "62668f2f-4526-4d61-a3da-2e9e3d764584",
        "type": "ZONE_STATUS",
        "eventDate": 1760162970000,
        "summary": "Backyard Orchard completed watering at 11:09 PM (PDT) for 273 minutes.",
        "subType": "ZONE_COMPLETED",
        "hidden": false,
        "topic": "WATERING"
    },
    {
        "id": "48f3000d-7d24-3343-9ce7-23f174e8acde",
        "deviceId": "62668f2f-4526-4d61-a3da-2e9e3d764584",
        "category": "SCHEDULE",
        "type": "SCHEDULE_STATUS",
        "eventDate": 1760162969000,
        "summary": "Orchard ran for 273 minutes.",
        "subType": "SCHEDULE_COMPLETED",
        "hidden": false,
        "scheduleId": "0dc08767-6cfd-45e9-b813-9d349786f8fc",
        "topic": "WATERING"
    },
    {
        "id": "e5077b46-cdaf-33eb-acb9-9ecab65c5157",
        "deviceId": "62668f2f-4526-4d61-a3da-2e9e3d764584",
        "category": "SCHEDULE",
        "eventDate": 1760146603000,
        "summary": "Orchard was not skipped because the PLUS weather network observed:\n0.00 in of predicted and 0.00 in observed precipitation\n57\u00b0F temp",
        "hidden": false,
        "scheduleId": "0dc08767-6cfd-45e9-b813-9d349786f8fc"
    },
    {
        "id": "176a0299-0bae-34a3-9e14-3f6bb3feff0c",
        "deviceId": "62668f2f-4526-4d61-a3da-2e9e3d764584",
        "type": "ZONE_STATUS",
        "eventDate": 1760146562000,
        "summary": "Backyard Orchard began watering at 06:36 PM (PDT).",
        "subType": "ZONE_STARTED",
        "hidden": false,
        "topic": "WATERING"
    },
    {
        "id": "b4f00f80-deb6-37b4-bd96-86f615f30daa",
        "deviceId": "62668f2f-4526-4d61-a3da-2e9e3d764584",
        "category": "SCHEDULE",
        "type": "SCHEDULE_STATUS",
        "eventDate": 1760146560000,
        "summary": "Orchard will run for 273 minutes.",
        "subType": "SCHEDULE_STARTED",
        "hidden": false,
        "scheduleId": "0dc08767-6cfd-45e9-b813-9d349786f8fc",
        "topic": "WATERING"
    },
    {
        "id": "0ca39cf2-2e57-3bd2-aa9d-07edea89b398",
        "deviceId": "62668f2f-4526-4d61-a3da-2e9e3d764584",
        "category": "SCHEDULE",
        "type": "SCHEDULE_STATUS",
        "eventDate": 1760105462000,
        "summary": "Lawn Sprinklers ran for 60 minutes.",
        "subType": "SCHEDULE_COMPLETED",
        "hidden": false,
        "scheduleId": "f7e02fa5-b1fc-4514-9f64-d76ccdd520d8",
        "topic": "WATERING"
    },
    {
        "id": "6d776cce-3c1d-326f-b487-656025620a48",
        "deviceId": "62668f2f-4526-4d61-a3da-2e9e3d764584",
        "type": "ZONE_STATUS",
        "eventDate": 1760105461000,
        "summary": "Backyard East Lawn completed watering at 07:11 AM (PDT) for 7 minutes.",
        "subType": "ZONE_COMPLETED",
        "hidden": false,
        "topic": "WATERING"
    },
    {
        "id": "708a7dcf-f956-3e1a-afbc-2f0cf529840f",
        "deviceId": "62668f2f-4526-4d61-a3da-2e9e3d764584",
        "type": "ZONE_STATUS",
        "eventDate": 1760105034000,
        "summary": "Backyard Middle We... completed watering at 07:03 AM (PDT) for 4 minutes.",
        "subType": "ZONE_COMPLETED",
        "hidden": false,
        "topic": "WATERING"
    },
    {
        "id": "c8f3bab2-a46e-3291-845f-df8f3cf42d92",
        "deviceId": "62668f2f-4526-4d61-a3da-2e9e3d764584",
        "type": "ZONE_STATUS",
        "eventDate": 1760105024000,
        "summary": "Backyard East Lawn began watering at 07:03 AM (PDT).",
        "subType": "ZONE_STARTED",
        "hidden": false,
        "topic": "WATERING"
    },
    {
        "id": "7b5eba7e-902d-36ff-a94b-49e51cdecb87",
        "deviceId": "62668f2f-4526-4d61-a3da-2e9e3d764584",
        "type": "ZONE_STATUS",
        "eventDate": 1760104775000,
        "summary": "Backyard Northwest completed watering at 06:59 AM (PDT) for 5 minutes.",
        "subType": "ZONE_COMPLETED",
        "hidden": false,
        "topic": "WATERING"
    },
    {
        "id": "beb6efca-ab0e-3586-891a-74c5e28ff3c1",
        "deviceId": "62668f2f-4526-4d61-a3da-2e9e3d764584",
        "type": "ZONE_STATUS",
        "eventDate": 1760104765000,
        "summary": "Backyard Middle We... began watering at 06:59 AM (PDT).",
        "subType": "ZONE_STARTED",
        "hidden": false,
        "topic": "WATERING"
    },
    {
        "id": "d065d421-5ca8-30d6-a120-3c50513313cf",
        "deviceId": "62668f2f-4526-4d61-a3da-2e9e3d764584",
        "type": "ZONE_STATUS",
        "eventDate": 1760104479000,
        "summary": "Backyard Northwest began watering at 06:54 AM (PDT).",
        "subType": "ZONE_STARTED",
        "hidden": false,
        "topic": "WATERING"
    },
    {
        "id": "230725ed-7b39-36e9-a2ff-807eb2389954",
        "deviceId": "62668f2f-4526-4d61-a3da-2e9e3d764584",
        "type": "DEVICE_STATUS",
        "eventDate": 1760104478000,
        "summary": "Soaked Backyard East Lawn for 21 minutes, completed at 06:54 AM (PDT).",
        "subType": "ZONE_CYCLING_COMPLETED",
        "hidden": false,
        "topic": "WATERING"
    },
    {
        "id": "ca4c7b6a-1e58-3bc9-baa5-0da66211e649",
        "deviceId": "62668f2f-4526-4d61-a3da-2e9e3d764584",
        "type": "ZONE_STATUS",
        "eventDate": 1760103236000,
        "summary": "Soaking Backyard East Lawn for 21 minutes, started at 06:33 AM (PDT).",
        "subType": "ZONE_CYCLING",
        "hidden": false,
        "topic": "WATERING"
    },
    {
        "id": "1064bbc5-7df2-3071-91e3-4dc61a321e6b",
        "deviceId": "62668f2f-4526-4d61-a3da-2e9e3d764584",
        "type": "ZONE_STATUS",
        "eventDate": 1760103234000,
        "summary": "Backyard East Lawn completed watering at 06:33 AM (PDT) for 7 minutes.",
        "subType": "ZONE_COMPLETED",
        "hidden": false,
        "topic": "WATERING"
    },
    {
        "id": "abc6501f-b9a9-344c-a44f-8b94cd559f8d",
        "deviceId": "62668f2f-4526-4d61-a3da-2e9e3d764584",
        "type": "ZONE_STATUS",
        "eventDate": 1760102806000,
        "summary": "Backyard South Wes... completed watering at 06:26 AM (PDT) for 6 minutes.",
        "subType": "ZONE_COMPLETED",
        "hidden": false,
        "topic": "WATERING"
    },
    {
        "id": "14f4f5c1-13a3-3d61-927f-1b570b06d769",
        "deviceId": "62668f2f-4526-4d61-a3da-2e9e3d764584",
        "type": "ZONE_STATUS",
        "eventDate": 1760102796000,
        "summary": "Backyard East Lawn began watering at 06:26 AM (PDT).",
        "subType": "ZONE_STARTED",
        "hidden": false,
        "topic": "WATERING"
    },
    {
        "id": "60e1ccd0-81e6-3dd5-aafb-dcbf46153dd8",
        "deviceId": "62668f2f-4526-4d61-a3da-2e9e3d764584",
        "type": "ZONE_STATUS",
        "eventDate": 1760102436000,
        "summary": "Backyard Middle We... completed watering at 06:20 AM (PDT) for 4 minutes.",
        "subType": "ZONE_COMPLETED",
        "hidden": false,
        "topic": "WATERING"
    },
    {
        "id": "e3705701-98aa-356c-a292-0c9887251fd4",
        "deviceId": "62668f2f-4526-4d61-a3da-2e9e3d764584",
        "type": "ZONE_STATUS",
        "eventDate": 1760102426000,
        "summary": "Backyard South Wes... began watering at 06:20 AM (PDT).",
        "subType": "ZONE_STARTED",
        "hidden": false,
        "topic": "WATERING"
    },
    {
        "id": "f5f3b034-9d91-32ec-904c-11d7d5e2662b",
        "deviceId": "62668f2f-4526-4d61-a3da-2e9e3d764584",
        "category": "SCHEDULE",
        "eventDate": 1760102224000,
        "summary": "Lawn Sprinklers was not skipped because the PLUS weather network observed:\n0.00 in of predicted and 0.00 in observed precipitation\n4 mph winds\n52\u00b0F temp",
        "hidden": false,
        "scheduleId": "f7e02fa5-b1fc-4514-9f64-d76ccdd520d8"
    },
    {
        "id": "df8f5d11-0ac2-3045-a8f3-9d150ab85e3b",
        "deviceId": "62668f2f-4526-4d61-a3da-2e9e3d764584",
        "type": "ZONE_STATUS",
        "eventDate": 1760102178000,
        "summary": "Backyard Northwest completed watering at 06:16 AM (PDT) for 5 minutes.",
        "subType": "ZONE_COMPLETED",
        "hidden": false,
        "topic": "WATERING"
    },
    {
        "id": "d072be66-1841-34ca-bc86-c6604e62968f",
        "deviceId": "62668f2f-4526-4d61-a3da-2e9e3d764584",
        "type": "ZONE_STATUS",
        "eventDate": 1760102167000,
        "summary": "Backyard Middle We... began watering at 06:16 AM (PDT).",
        "subType": "ZONE_STARTED",
        "hidden": false,
        "topic": "WATERING"
    },
    {
        "id": "e514c4e8-3b05-338f-aa8e-584f0ec93bf1",
        "deviceId": "62668f2f-4526-4d61-a3da-2e9e3d764584",
        "type": "ZONE_STATUS",
        "eventDate": 1760101881000,
        "summary": "Backyard Northwest began watering at 06:11 AM (PDT).",
        "subType": "ZONE_STARTED",
        "hidden": false,
        "topic": "WATERING"
    },
    {
        "id": "a3a37263-76d6-330e-ba8f-b92bf598ab9c",
        "deviceId": "62668f2f-4526-4d61-a3da-2e9e3d764584",
        "category": "SCHEDULE",
        "type": "SCHEDULE_STATUS",
        "eventDate": 1760101880000,
        "summary": "Lawn Sprinklers will run for 60 minutes.",
        "subType": "SCHEDULE_STARTED",
        "hidden": false,
        "scheduleId": "f7e02fa5-b1fc-4514-9f64-d76ccdd520d8",
        "topic": "WATERING"
    },
    {
        "id": "5b8ffb6f-e07f-3e29-bce3-2fac3e789149",
        "deviceId": "62668f2f-4526-4d61-a3da-2e9e3d764584",
        "type": "ZONE_STATUS",
        "eventDate": 1759983658000,
        "summary": "Front Yard Tree completed watering at 09:20 PM (PDT) for 144 minutes.",
        "subType": "ZONE_COMPLETED",
        "hidden": false,
        "topic": "WATERING"
    },
    {
        "id": "6e5ab516-1e3c-37d9-bd2b-768605cf9ec6",
        "deviceId": "62668f2f-4526-4d61-a3da-2e9e3d764584",
        "category": "SCHEDULE",
        "type": "SCHEDULE_STATUS",
        "eventDate": 1759983657000,
        "summary": "Front Yard ran for 154 minutes.",
        "subType": "SCHEDULE_COMPLETED",
        "hidden": false,
        "scheduleId": "143ee9ea-88f8-48dd-b134-e9fae4e9005b",
        "topic": "WATERING"
    },
    {
        "id": "4fccd65d-3fde-3a6e-a578-d1bda45ca468",
        "deviceId": "62668f2f-4526-4d61-a3da-2e9e3d764584",
        "type": "ZONE_STATUS",
        "eventDate": 1759975039000,
        "summary": "Front Yard completed watering at 06:57 PM (PDT) for 10 minutes.",
        "subType": "ZONE_COMPLETED",
        "hidden": false,
        "topic": "WATERING"
    },
    {
        "id": "2f7197a3-494d-3a9b-93b3-f0f2d07a901a",
        "deviceId": "62668f2f-4526-4d61-a3da-2e9e3d764584",
        "type": "ZONE_STATUS",
        "eventDate": 1759975029000,
        "summary": "Front Yard Tree began watering at 06:57 PM (PDT).",
        "subType": "ZONE_STARTED",
        "hidden": false,
        "topic": "WATERING"
    },
    {
        "id": "ea2fc979-6256-3cb9-94a0-3d83c9684fbf",
        "deviceId": "62668f2f-4526-4d61-a3da-2e9e3d764584",
        "category": "SCHEDULE",
        "eventDate": 1759974662000,
        "summary": "Front Yard was not skipped because the PLUS weather network observed:\n0.00 in of predicted and 0.00 in observed precipitation\n11 mph winds\n61\u00b0F temp",
        "hidden": false,
        "scheduleId": "143ee9ea-88f8-48dd-b134-e9fae4e9005b"
    },
    {
        "id": "394efabb-9bc4-35dc-ad25-86abc777c04a",
        "deviceId": "62668f2f-4526-4d61-a3da-2e9e3d764584",
        "type": "ZONE_STATUS",
        "eventDate": 1759974441000,
        "summary": "Front Yard began watering at 06:47 PM (PDT).",
        "subType": "ZONE_STARTED",
        "hidden": false,
        "topic": "WATERING"
    },
    {
        "id": "54348e94-f0ba-31a5-97db-b9f778acd992",
        "deviceId": "62668f2f-4526-4d61-a3da-2e9e3d764584",
        "category": "SCHEDULE",
        "type": "SCHEDULE_STATUS",
        "eventDate": 1759974440000,
        "summary": "Front Yard will run for 154 minutes.",
        "subType": "SCHEDULE_STARTED",
        "hidden": false,
        "scheduleId": "143ee9ea-88f8-48dd-b134-e9fae4e9005b",
        "topic": "WATERING"
    },
    {
        "id": "52c25547-49e0-3f6d-8893-c472f77e1f8b",
        "deviceId": "62668f2f-4526-4d61-a3da-2e9e3d764584",
        "category": "SCHEDULE",
        "type": "SCHEDULE_STATUS",
        "eventDate": 1759974440000,
        "summary": "Bubblers ran for 8 minutes.",
        "subType": "SCHEDULE_COMPLETED",
        "hidden": false,
        "scheduleId": "e5d592d2-06a3-4c10-9e9c-11a656e12650",
        "topic": "WATERING"
    },
    {
        "id": "f4b9b065-12d4-3700-b4fa-2fc344afefe0",
        "deviceId": "62668f2f-4526-4d61-a3da-2e9e3d764584",
        "type": "ZONE_STATUS",
        "eventDate": 1759974439000,
        "summary": "Backyard Bubblers completed watering at 06:47 PM (PDT) for 8 minutes.",
        "subType": "ZONE_COMPLETED",
        "hidden": false,
        "topic": "WATERING"
    },
    {
        "id": "05e290c9-b511-34a2-9f60-1134a655eb52",
        "deviceId": "62668f2f-4526-4d61-a3da-2e9e3d764584",
        "category": "SCHEDULE",
        "eventDate": 1759974094000,
        "summary": "Bubblers was not skipped because the PLUS weather network observed:\n0.00 in of predicted and 0.00 in observed precipitation\n11 mph winds\n68\u00b0F temp",
        "hidden": false,
        "scheduleId": "e5d592d2-06a3-4c10-9e9c-11a656e12650"
    },
    {
        "id": "2f460b32-78cc-34ff-8d58-8338339eae65",
        "deviceId": "62668f2f-4526-4d61-a3da-2e9e3d764584",
        "type": "ZONE_STATUS",
        "eventDate": 1759973942000,
        "summary": "Backyard Bubblers began watering at 06:39 PM (PDT).",
        "subType": "ZONE_STARTED",
        "hidden": false,
        "topic": "WATERING"
    },
    {
        "id": "e251e4cd-5afe-3fad-9567-a88b30d318b7",
        "deviceId": "62668f2f-4526-4d61-a3da-2e9e3d764584",
        "category": "SCHEDULE",
        "type": "SCHEDULE_STATUS",
        "eventDate": 1759973940000,
        "summary": "Bubblers will run for 8 minutes.",
        "subType": "SCHEDULE_STARTED",
        "hidden": false,
        "scheduleId": "e5d592d2-06a3-4c10-9e9c-11a656e12650",
        "topic": "WATERING"
    },
    {
        "id": "a9e0e2d5-3e3e-3fbf-88f6-6d4e046b2eb3",
        "deviceId": "62668f2f-4526-4d61-a3da-2e9e3d764584",
        "category": "DEVICE",
        "type": "DEVICE_STATUS",
        "eventDate": 1759960673000,
        "summary": "Davis 16 has turned off and back on. This is usually not a problem. If power cycles continue, please contact Rachio Support.",
        "subType": "COLD_REBOOT",
        "hidden": false,
        "topic": "DEVICE"
    },
    {
        "id": "b9fe1e58-2d50-303e-8865-a0645a53ebc8",
        "deviceId": "62668f2f-4526-4d61-a3da-2e9e3d764584",
        "category": "SCHEDULE",
        "type": "SCHEDULE_STATUS",
        "eventDate": 1759846082000,
        "summary": "Lawn Sprinklers ran for 60 minutes.",
        "subType": "SCHEDULE_COMPLETED",
        "hidden": false,
        "scheduleId": "f7e02fa5-b1fc-4514-9f64-d76ccdd520d8",
        "topic": "WATERING"
    },
    {
        "id": "52659d71-1006-3c55-ba49-052f3ada2042",
        "deviceId": "62668f2f-4526-4d61-a3da-2e9e3d764584",
        "type": "ZONE_STATUS",
        "eventDate": 1759846081000,
        "summary": "Backyard East Lawn completed watering at 07:08 AM (PDT) for 7 minutes.",
        "subType": "ZONE_COMPLETED",
        "hidden": false,
        "topic": "WATERING"
    },
    {
        "id": "b96f7315-f07f-32f1-94ca-c43d26ec8f70",
        "deviceId": "62668f2f-4526-4d61-a3da-2e9e3d764584",
        "type": "ZONE_STATUS",
        "eventDate": 1759845654000,
        "summary": "Backyard Middle We... completed watering at 07:00 AM (PDT) for 4 minutes.",
        "subType": "ZONE_COMPLETED",
        "hidden": false,
        "topic": "WATERING"
    },
    {
        "id": "8e8442ee-5573-3fc3-bebb-4925978ba606",
        "deviceId": "62668f2f-4526-4d61-a3da-2e9e3d764584",
        "type": "ZONE_STATUS",
        "eventDate": 1759845645000,
        "summary": "Backyard East Lawn began watering at 07:00 AM (PDT).",
        "subType": "ZONE_STARTED",
        "hidden": false,
        "topic": "WATERING"
    },
    {
        "id": "95ff6704-2548-3498-8a4a-a2bc773146ed",
        "deviceId": "62668f2f-4526-4d61-a3da-2e9e3d764584",
        "type": "ZONE_STATUS",
        "eventDate": 1759845395000,
        "summary": "Backyard Northwest completed watering at 06:56 AM (PDT) for 5 minutes.",
        "subType": "ZONE_COMPLETED",
        "hidden": false,
        "topic": "WATERING"
    },
    {
        "id": "ad9ff363-9a25-3780-b784-15bd476d3c2c",
        "deviceId": "62668f2f-4526-4d61-a3da-2e9e3d764584",
        "type": "ZONE_STATUS",
        "eventDate": 1759845385000,
        "summary": "Backyard Middle We... began watering at 06:56 AM (PDT).",
        "subType": "ZONE_STARTED",
        "hidden": false,
        "topic": "WATERING"
    },
    {
        "id": "e886b262-9139-35fb-bd0a-4de47b2ddb3f",
        "deviceId": "62668f2f-4526-4d61-a3da-2e9e3d764584",
        "type": "ZONE_STATUS",
        "eventDate": 1759845099000,
        "summary": "Backyard Northwest began watering at 06:51 AM (PDT).",
        "subType": "ZONE_STARTED",
        "hidden": false,
        "topic": "WATERING"
    },
    {
        "id": "ac532605-3802-3ee6-abd8-121432c79c4b",
        "deviceId": "62668f2f-4526-4d61-a3da-2e9e3d764584",
        "type": "DEVICE_STATUS",
        "eventDate": 1759845098000,
        "summary": "Soaked Backyard East Lawn for 21 minutes, completed at 06:51 AM (PDT).",
        "subType": "ZONE_CYCLING_COMPLETED",
        "hidden": false,
        "topic": "WATERING"
    },
    {
        "id": "63a44699-32a2-3a01-83f5-4646ac7995bd",
        "deviceId": "62668f2f-4526-4d61-a3da-2e9e3d764584",
        "type": "ZONE_STATUS",
        "eventDate": 1759843855000,
        "summary": "Soaking Backyard East Lawn for 21 minutes, started at 06:30 AM (PDT).",
        "subType": "ZONE_CYCLING",
        "hidden": false,
        "topic": "WATERING"
    },
    {
        "id": "8052ea0e-c2ab-3843-ab5c-ed0a44ad1f77",
        "deviceId": "62668f2f-4526-4d61-a3da-2e9e3d764584",
        "type": "ZONE_STATUS",
        "eventDate": 1759843854000,
        "summary": "Backyard East Lawn completed watering at 06:30 AM (PDT) for 7 minutes.",
        "subType": "ZONE_COMPLETED",
        "hidden": false,
        "topic": "WATERING"
    },
    {
        "id": "7663c5bd-752b-3407-8369-0b46641252c7",
        "deviceId": "62668f2f-4526-4d61-a3da-2e9e3d764584",
        "type": "ZONE_STATUS",
        "eventDate": 1759843426000,
        "summary": "Backyard South Wes... completed watering at 06:23 AM (PDT) for 6 minutes.",
        "subType": "ZONE_COMPLETED",
        "hidden": false,
        "topic": "WATERING"
    },
    {
        "id": "9bad0212-540f-33d7-b6c6-521db7c70f86",
        "deviceId": "62668f2f-4526-4d61-a3da-2e9e3d764584",
        "type": "ZONE_STATUS",
        "eventDate": 1759843416000,
        "summary": "Backyard East Lawn began watering at 06:23 AM (PDT).",
        "subType": "ZONE_STARTED",
        "hidden": false,
        "topic": "WATERING"
    },
    {
        "id": "6a7c5893-bab1-3f08-88df-742e0caa80bd",
        "deviceId": "62668f2f-4526-4d61-a3da-2e9e3d764584",
        "type": "ZONE_STATUS",
        "eventDate": 1759843056000,
        "summary": "Backyard Middle We... completed watering at 06:17 AM (PDT) for 4 minutes.",
        "subType": "ZONE_COMPLETED",
        "hidden": false,
        "topic": "WATERING"
    },
    {
        "id": "539b84aa-22cc-303f-a38b-29ac6c626ee1",
        "deviceId": "62668f2f-4526-4d61-a3da-2e9e3d764584",
        "type": "ZONE_STATUS",
        "eventDate": 1759843047000,
        "summary": "Backyard South Wes... began watering at 06:17 AM (PDT).",
        "subType": "ZONE_STARTED",
        "hidden": false,
        "topic": "WATERING"
    },
    {
        "id": "48662ca3-a889-3dd7-b383-e4c8ce7482b5",
        "deviceId": "62668f2f-4526-4d61-a3da-2e9e3d764584",
        "type": "ZONE_STATUS",
        "eventDate": 1759842797000,
        "summary": "Backyard Northwest completed watering at 06:13 AM (PDT) for 5 minutes.",
        "subType": "ZONE_COMPLETED",
        "hidden": false,
        "topic": "WATERING"
    },
    {
        "id": "9fed1490-d13c-3bff-8074-f9bb19582f21",
        "deviceId": "62668f2f-4526-4d61-a3da-2e9e3d764584",
        "type": "ZONE_STATUS",
        "eventDate": 1759842787000,
        "summary": "Backyard Middle We... began watering at 06:13 AM (PDT).",
        "subType": "ZONE_STARTED",
        "hidden": false,
        "topic": "WATERING"
    },
    {
        "id": "b0414b7d-95bf-354a-aac7-38b526631210",
        "deviceId": "62668f2f-4526-4d61-a3da-2e9e3d764584",
        "category": "SCHEDULE",
        "eventDate": 1759842701000,
        "summary": "Lawn Sprinklers was not skipped because the PLUS weather network observed:\n0.00 in of predicted and 0.00 in observed precipitation\n7 mph winds\n55\u00b0F temp",
        "hidden": false,
        "scheduleId": "f7e02fa5-b1fc-4514-9f64-d76ccdd520d8"
    },
    {
        "id": "e59b0974-df8e-35de-ae7e-b7fa8990b70e",
        "deviceId": "62668f2f-4526-4d61-a3da-2e9e3d764584",
        "type": "ZONE_STATUS",
        "eventDate": 1759842501000,
        "summary": "Backyard Northwest began watering at 06:08 AM (PDT).",
        "subType": "ZONE_STARTED",
        "hidden": false,
        "topic": "WATERING"
    },
    {
        "id": "3e8cc3ca-5e44-3d00-b490-ce2525350bf3",
        "deviceId": "62668f2f-4526-4d61-a3da-2e9e3d764584",
        "category": "SCHEDULE",
        "type": "SCHEDULE_STATUS",
        "eventDate": 1759842500000,
        "summary": "Lawn Sprinklers will run for 60 minutes.",
        "subType": "SCHEDULE_STARTED",
        "hidden": false,
        "scheduleId": "f7e02fa5-b1fc-4514-9f64-d76ccdd520d8",
        "topic": "WATERING"
    }
]